tkin_new/__init__.py
tkin_new-0.2.dist-info/LICENSE.txt
tkin_new-0.2.dist-info/METADATA
tkin_new-0.2.dist-info/WHEEL
tkin_new-0.2.dist-info/top_level.txt
tkin_new-0.2.dist-info/RECORD
