Metadata-Version: 2.1
Name: tkin-new
Version: 0.2
Summary: tki
Home-page: UNKNOWN
Author: klmsathish
Author-email: klmsathish@gmail.com
License: MIT
Keywords: tkinter
Platform: UNKNOWN
